{
  "flash_request": {
    "schema_type": "FLASH_REQUEST",
    "item_meta": {
      "parsed_item": "Calculus textbook",
      "category": "textbooks",
      "tags": [
        "math",
        "calculus"
      ]
    },
    "item_attributes": {
      "primary": {
        "size": null,
        "color": null,
        "condition_requested": null
      },
      "secondary": {
        "material": null,
        "brand": null
      }
    },
    "transaction": {
      "type_preferred": "buy",
      "type_acceptable": [
        "buy"
      ],
      "price_max": null
    },
    "context": {
      "urgency": "medium",
      "reason": null,
      "original_text": "Looking for a Calculus textbook for MATH 101."
    },
    "location": {
      "text_input": null,
      "device_gps": null
    }
  },
  "seller_profile": {
    "schema_type": "SELLER_PROFILE",
    "user_id": "math_whiz_seller_22",
    "context": {
      "original_text": "Math major selling old textbooks and notes, especially for lower-division courses. Also have some old electronics."
    },
    "profile_keywords": [
      "math",
      "textbooks",
      "calculus",
      "notes",
      "used books",
      "electronics"
    ],
    "inferred_major": "Mathematics",
    "inferred_location_keywords": [
      "math building",
      "library",
      "campus center"
    ],
    "sales_history_summary": [
      {
        "category": "textbooks",
        "item_examples": [
          "Calculus Textbook",
          "Linear Algebra Notes"
        ],
        "total_items_sold": 18,
        "avg_price_per_item": 38.5,
        "dominant_transaction_type_in_category": "sell"
      },
      {
        "category": "electronics",
        "item_examples": [
          "Old HDMI Cable",
          "USB Drive"
        ],
        "total_items_sold": 3,
        "avg_price_per_item": 10.0,
        "dominant_transaction_type_in_category": "sell"
      }
    ],
    "overall_dominant_transaction_type": "sell",
    "related_categories_of_interest": [
      "textbooks",
      "school_supplies",
      "electronics"
    ]
  },
  "actual_item": {
    "schema_type": "FLASH_REQUEST",
    "item_meta": {
      "parsed_item": "Calculus: Early Transcendentals, 9th Edition",
      "category": "textbooks",
      "tags": [
        "math",
        "calculus",
        "textbook",
        "stewart"
      ]
    },
    "item_attributes": {
      "primary": {
        "size": "standard textbook",
        "color": "blue",
        "condition_requested": [
          "used",
          "good"
        ]
      },
      "secondary": {
        "material": "paper",
        "brand": "Cengage"
      }
    },
    "transaction": {
      "type_preferred": "buy",
      "type_acceptable": [
        "buy",
        "borrow"
      ],
      "price_max": 45.0
    },
    "context": {
      "urgency": "low",
      "reason": "finished course, no longer needed",
      "original_text": "Selling my Calculus textbook (Stewart, 9th Ed.). Good condition, lightly used. Asking $45."
    },
    "location": {
      "text_input": "dorm room, Building C",
      "device_gps": {
        "lat": 34.0722,
        "lng": -118.4446
      }
    }
  },
  "outcome_label": "positive"
}